itemseg/__about__.py
itemseg/__init__.py
itemseg/__main__.py
itemseg/crf_feature_lib_v8.py
itemseg/gpt4itemSeg.py
itemseg/lib_10kq_seg_v1.py
itemseg/test_textfilter.py
itemseg/.ipynb_checkpoints/__about__-checkpoint.py
itemseg/.ipynb_checkpoints/__init__-checkpoint.py
itemseg/.ipynb_checkpoints/lib_10kq_seg_v1-checkpoint.py
itemseg-3.4.0.dist-info/METADATA
itemseg-3.4.0.dist-info/WHEEL
itemseg-3.4.0.dist-info/entry_points.txt
itemseg-3.4.0.dist-info/licenses/LICENSE.txt
itemseg-3.4.0.dist-info/RECORD
