Metadata-Version: 2.4
Name: itemseg
Version: 3.4.0
Summary: The 10-K Report Item Segmentation Tool
Project-URL: Documentation, https://github.com/hsinmin/itemseg#readme
Project-URL: Issues, https://github.com/hsinmin/itemseg/issues
Project-URL: Source, https://github.com/hsinmin/itemseg
Author-email: "Hsin-Min Lu; Huan-Hsun Yen; Yen-Hsiu Chen" <luim@ntu.edu.tw>
License-File: LICENSE.txt
Keywords: 10-K,BERT,CRF,ChatGPT,Item Segmentation,LSTM,Sequence Labeling
Classifier: Development Status :: 4 - Beta
Classifier: License :: Free for non-commercial use
Classifier: Programming Language :: Python
Classifier: Programming Language :: Python :: 3.8
Classifier: Programming Language :: Python :: 3.9
Classifier: Programming Language :: Python :: 3.10
Classifier: Programming Language :: Python :: 3.11
Classifier: Programming Language :: Python :: 3.12
Classifier: Programming Language :: Python :: 3.13
Classifier: Programming Language :: Python :: Implementation :: CPython
Classifier: Programming Language :: Python :: Implementation :: PyPy
Requires-Python: >=3.8
Requires-Dist: gensim<=4.4.0
Requires-Dist: inscriptis<=2.7.0
Requires-Dist: nltk<=3.9.2
Requires-Dist: numpy<=2.4.1
Requires-Dist: openai<=2.15.0
Requires-Dist: pandas<=2.3.3
Requires-Dist: python-crfsuite>=0.9.12
Requires-Dist: requests<=2.32.5
Requires-Dist: scikit-learn<=1.8.0
Requires-Dist: scipy<=1.17.0
Requires-Dist: sentence-transformers<=5.2.0
Requires-Dist: torch<=2.9.1
Requires-Dist: urllib3<=2.6.3
